Metadata-Version: 2.1
Name: bio96
Version: 0.5.1
Summary: File format for 96-well plate layouts
Home-page: https://github.com/kalekundert/bio96
Author: Kale Kundert
Author-email: kale@thekunderts.net
License: MIT
Keywords: bio96
Platform: UNKNOWN
Classifier: Development Status :: 3 - Alpha
Classifier: Intended Audience :: Developers
Classifier: License :: OSI Approved :: MIT License
Classifier: Natural Language :: English
Classifier: Programming Language :: Python :: 3.6
Classifier: Topic :: Scientific/Engineering :: Bio-Informatics
Provides-Extra: docs
